{"stat.leaveGame":37,"stat.useItem.minecraft.chicken":8,"stat.jump":3538,"stat.swimOneCm":14736,"stat.useItem.minecraft.sand":5,"stat.fallOneCm":159342,"stat.useItem.minecraft.planks":16,"stat.crouchOneCm":23849,"stat.useItem.minecraft.dirt":9,"achievement.exploreAllBiomes":{"value":0,"progress":["ForestHills","Roofed Forest","Birch Forest","Plains","The End","Beach","Extreme Hills+","Ice Plains","Forest","Extreme Hills","Deep Ocean","Hell","Savanna"]},"stat.mineBlock.minecraft.red_mushroom":12,"stat.useItem.minecraft.sapling":1,"stat.damageTaken":12565,"stat.flyOneCm":961754,"stat.mineBlock.minecraft.sand":7,"stat.useItem.minecraft.red_mushroom":11,"stat.mineBlock.minecraft.gravel":16,"stat.killEntity.Villager":2,"stat.damageDealt":1720,"stat.killEntity.Rabbit":1,"stat.useItem.minecraft.wool":435,"stat.timeSinceDeath":603620,"stat.mineBlock.minecraft.dirt":9,"stat.useItem.minecraft.sign":2,"stat.walkOneCm":1675448,"stat.playerKills":3,"stat.useItem.minecraft.log":6,"stat.killEntity.Wolf":1,"stat.useItem.minecraft.gravel":13,"stat.useItem.minecraft.cooked_porkchop":35,"stat.talkedToVillager":3,"stat.mineBlock.minecraft.wool":433,"achievement.mineWood":11,"stat.sprintOneCm":432548,"achievement.openInventory":22,"stat.craftItem.minecraft.planks":16,"stat.killEntity.Chicken":8,"stat.useItem.minecraft.flint_and_steel":1,"stat.mobKills":12,"stat.mineBlock.minecraft.log":14,"stat.deaths":36,"stat.drop":6,"stat.mineBlock.minecraft.leaves":14,"stat.playOneMinute":3766081,"stat.useItem.minecraft.shears":410,"stat.diveOneCm":13462}